BanditAgents/__init__.py
BanditAgents/mocks/__init__.py
BanditAgents/mocks/builders/__init__.py
BanditAgents/mocks/builders/contexts_builders/__init__.py
BanditAgents/mocks/builders/contexts_builders/simulation_context_builder.py
BanditAgents/mocks/builders/solvers_builders/__init__.py
BanditAgents/mocks/builders/solvers_builders/base_solver_builder.py
BanditAgents/src/__init__.py
BanditAgents/src/agents/__init__.py
BanditAgents/src/agents/agent.py
BanditAgents/src/contexts/__init__.py
BanditAgents/src/contexts/context.py
BanditAgents/src/contexts/simulation_context.py
BanditAgents/src/domain/__init__.py
BanditAgents/src/domain/context_action_args.py
BanditAgents/src/domain/solver_args.py
BanditAgents/src/domain/hyperparameters/__init__.py
BanditAgents/src/solvers/__init__.py
BanditAgents/src/solvers/base_solver.py
BanditAgents/src/solvers/epsilon_solver.py
BanditAgents/src/solvers/sampling_solver.py
BanditAgents/src/solvers/ucb_solver.py
BanditAgents/src/solvers/weight_solver.py
Exemples/__init__.py
Exemples/agents_exemples/__init__.py
Exemples/agents_exemples/basic_agent_exemple.py
Exemples/basic_exemples/__init__.py
Exemples/basic_exemples/epsilon_solver_example.py
Exemples/basic_exemples/sampling_solver_example.py
Exemples/basic_exemples/ucb_solver_example.py
Exemples/basic_exemples/weight_solver_example.py
Tests/__init__.py
Tests/BanditAgents/__init__.py
Tests/BanditAgents/src/__init__.py
Tests/BanditAgents/src/solvers/__init__.py
Tests/BanditAgents/src/solvers/test_base_solver.py
Tests/BanditAgents/src/solvers/test_epsilon_solver.py
Tests/BanditAgents/src/solvers/test_sampling_solver.py
Tests/BanditAgents/src/solvers/test_ucb_solver.py
Tests/BanditAgents/src/solvers/test_weight_solver.py
Bandit_Problem_Solvers-0.5.0.dist-info/LICENSE
Bandit_Problem_Solvers-0.5.0.dist-info/METADATA
Bandit_Problem_Solvers-0.5.0.dist-info/WHEEL
Bandit_Problem_Solvers-0.5.0.dist-info/top_level.txt
Bandit_Problem_Solvers-0.5.0.dist-info/RECORD
