Metadata-Version: 2.1
Name: Bandit-Problem-Solvers
Version: 0.5.0
Summary: Library to solve k-armed bandit problems
Author: Vincent Martel
Author-email: vincent.martel.11235@gmail.com
License-File: LICENSE
Requires-Dist: numpy==2.1.3
Requires-Dist: scipy==1.14.1
